{"nm":"Main Scene","ddd":0,"h":418,"w":418,"meta":{"g":"@lottiefiles/creator 1.62.0"},"layers":[{"ty":4,"nm":"HAND1","sr":1,"st":0,"op":91,"ip":0,"hd":false,"ddd":0,"bm":0,"hasMask":false,"ao":0,"ks":{"a":{"a":0,"k":[-212.5,-87.135,0],"ix":1},"s":{"a":0,"k":[105.08000000000001,105.08],"ix":6},"sk":{"a":0,"k":0},"p":{"a":0,"k":[296.2403880481851,246.53898218749657],"ix":2},"r":{"a":1,"k":[{"o":{"x":0.4,"y":0},"i":{"x":0.4,"y":1},"s":[0],"t":16},{"o":{"x":0.4,"y":0},"i":{"x":0.4,"y":1},"s":[-4.256],"t":30.4},{"s":[0],"t":43.2}],"ix":10},"sa":{"a":0,"k":0},"o":{"a":0,"k":100,"ix":11}},"shapes":[{"ty":"gr","bm":0,"hd":false,"mn":"ADBE Vector Group","nm":"Shape 4","ix":1,"cix":2,"np":3,"it":[{"ty":"sh","bm":0,"hd":false,"mn":"ADBE Vector Shape - Group","nm":"Path 1","ix":1,"d":1,"ks":{"a":0,"k":{"c":false,"i":[[0,0],[8.125,-7.5],[-8.25,-4.75],[0,0],[-23.75,8.25],[-6.5,0.5],[0,0],[0,0]],"o":[[0,0],[-8.185,7.555],[8.25,4.75],[0,0],[23.75,-8.25],[6.5,-0.5],[0,0],[0,0]],"v":[[-331.625,-91.5],[-373,-107.25],[-371.25,-86.5],[-313.5,-52],[-266,-51.25],[-231.5,-63.25],[-213.25,-64.25],[-212.5,-111.75]]},"ix":2}},{"ty":"st","bm":0,"hd":false,"mn":"ADBE Vector Graphic - Stroke","nm":"Stroke 1","lc":2,"lj":1,"ml":4,"o":{"a":0,"k":100,"ix":4},"w":{"a":0,"k":5,"ix":5},"c":{"a":0,"k":[0.7804,0.5843,0.4392],"ix":3}},{"ty":"tr","a":{"a":0,"k":[0,0],"ix":1},"s":{"a":0,"k":[100,100],"ix":3},"sk":{"a":0,"k":0,"ix":4},"p":{"a":0,"k":[0,0],"ix":2},"r":{"a":0,"k":0,"ix":6},"sa":{"a":0,"k":0,"ix":5},"o":{"a":0,"k":100,"ix":7}}]},{"ty":"gr","bm":0,"hd":false,"mn":"ADBE Vector Group","nm":"Shape 3","ix":2,"cix":2,"np":3,"it":[{"ty":"sh","bm":0,"hd":false,"mn":"ADBE Vector Shape - Group","nm":"Path 1","ix":1,"d":1,"ks":{"a":0,"k":{"c":false,"i":[[0,0],[5.358,-0.536],[0,0]],"o":[[0,0],[-6.25,0.625],[0,0]],"v":[[-319.875,-98.125],[-358.25,-116.25],[-367.5,-108.875]]},"ix":2}},{"ty":"st","bm":0,"hd":false,"mn":"ADBE Vector Graphic - Stroke","nm":"Stroke 1","lc":2,"lj":1,"ml":4,"o":{"a":0,"k":100,"ix":4},"w":{"a":0,"k":5,"ix":5},"c":{"a":0,"k":[0.7804,0.5843,0.4392],"ix":3}},{"ty":"tr","a":{"a":0,"k":[0,0],"ix":1},"s":{"a":0,"k":[100,100],"ix":3},"sk":{"a":0,"k":0,"ix":4},"p":{"a":0,"k":[0,0],"ix":2},"r":{"a":0,"k":0,"ix":6},"sa":{"a":0,"k":0,"ix":5},"o":{"a":0,"k":100,"ix":7}}]},{"ty":"gr","bm":0,"hd":false,"mn":"ADBE Vector Group","nm":"Shape 2","ix":3,"cix":2,"np":3,"it":[{"ty":"sh","bm":0,"hd":false,"mn":"ADBE Vector Shape - Group","nm":"Path 1","ix":1,"d":1,"ks":{"a":0,"k":{"c":false,"i":[[0,0],[4.583,-1.029],[0,0]],"o":[[0,0],[-6.125,1.375],[0,0]],"v":[[-305,-101.625],[-346.75,-123],[-354.75,-116.375]]},"ix":2}},{"ty":"st","bm":0,"hd":false,"mn":"ADBE Vector Graphic - Stroke","nm":"Stroke 1","lc":2,"lj":1,"ml":4,"o":{"a":0,"k":100,"ix":4},"w":{"a":0,"k":5,"ix":5},"c":{"a":0,"k":[0.7804,0.5843,0.4392],"ix":3}},{"ty":"tr","a":{"a":0,"k":[0,0],"ix":1},"s":{"a":0,"k":[100,100],"ix":3},"sk":{"a":0,"k":0,"ix":4},"p":{"a":0,"k":[0,0],"ix":2},"r":{"a":0,"k":0,"ix":6},"sa":{"a":0,"k":0,"ix":5},"o":{"a":0,"k":100,"ix":7}}]},{"ty":"gr","bm":0,"hd":false,"mn":"ADBE Vector Group","nm":"Shape 1","ix":4,"cix":2,"np":3,"it":[{"ty":"sh","bm":0,"hd":false,"mn":"ADBE Vector Shape - Group","nm":"Path 1","ix":1,"d":1,"ks":{"a":0,"k":{"c":false,"i":[[0,0],[11.5,0.25],[8,-2],[1.25,-11],[-21.75,5.25],[0,0]],"o":[[0,0],[-11.5,-0.25],[-8,2],[0.75,11.5],[21.75,-5.25],[0,0]],"v":[[-213,-111.75],[-247,-126.5],[-302.5,-101.75],[-333.25,-87],[-304,-75.75],[-276.5,-84.25]]},"ix":2}},{"ty":"st","bm":0,"hd":false,"mn":"ADBE Vector Graphic - Stroke","nm":"Stroke 1","lc":2,"lj":1,"ml":4,"o":{"a":0,"k":100,"ix":4},"w":{"a":0,"k":5,"ix":5},"c":{"a":0,"k":[0.7804,0.5843,0.4392],"ix":3}},{"ty":"tr","a":{"a":0,"k":[0,0],"ix":1},"s":{"a":0,"k":[100,100],"ix":3},"sk":{"a":0,"k":0,"ix":4},"p":{"a":0,"k":[0,0],"ix":2},"r":{"a":0,"k":0,"ix":6},"sa":{"a":0,"k":0,"ix":5},"o":{"a":0,"k":100,"ix":7}}]}],"ind":1},{"ty":4,"nm":"Flame-2 fill","sr":1,"st":0,"op":844,"ip":0,"hd":false,"ddd":0,"bm":0,"hasMask":false,"ao":0,"ks":{"a":{"a":0,"k":[657.51,35,0],"ix":1},"s":{"a":0,"k":[38.53124127345626,42.07535419515865],"ix":6},"sk":{"a":0,"k":0},"p":{"a":0,"k":[200.98989987174323,192.23440608422976],"ix":2},"r":{"a":0,"k":0,"ix":10},"sa":{"a":0,"k":0},"o":{"a":0,"k":100,"ix":11}},"shapes":[{"ty":"gr","bm":1,"hd":false,"mn":"ADBE Vector Group","nm":"Group 1","ix":1,"cix":2,"np":2,"it":[{"ty":"gr","bm":0,"hd":false,"mn":"ADBE Vector Group","nm":"Group 1","ix":1,"cix":2,"np":2,"it":[{"ty":"sh","bm":0,"hd":false,"mn":"ADBE Vector Shape - Group","nm":"Path 1","ix":1,"d":1,"ks":{"a":1,"k":[{"o":{"x":0.167,"y":0},"i":{"x":0.833,"y":0.833},"s":[{"c":true,"i":[[-0.352,0.016],[0.352,0],[0.32,0.031],[-0.304,0]],"o":[[-0.336,0.031],[-0.32,0],[0.288,0.016],[0.368,0]],"v":[[4.969,-0.637],[3.945,-0.605],[2.985,-0.637],[3.881,-0.621]]}],"t":0},{"o":{"x":0.167,"y":0.167},"i":{"x":0.97,"y":1},"s":[{"c":true,"i":[[-0.34,0.025],[0.341,-0.009],[0.31,0.023],[-0.294,0.008]],"o":[[-0.325,0.041],[-0.31,0.008],[0.28,0.008],[0.357,-0.01]],"v":[[5.875,4.032],[4.885,4.091],[3.954,4.085],[4.822,4.077]]}],"t":4.8},{"o":{"x":0.333,"y":0},"i":{"x":0.667,"y":1},"s":[{"c":true,"i":[[-0.329,0.016],[0.329,0],[0.299,0.032],[-0.285,0]],"o":[[-0.315,0.032],[-0.3,0],[0.27,0.016],[0.345,0]],"v":[[4.931,13.301],[3.972,13.334],[3.073,13.301],[3.912,13.318]]}],"t":11.2},{"o":{"x":0.167,"y":0.167},"i":{"x":0.833,"y":0.833},"s":[{"c":true,"i":[[-0.323,0.016],[0.323,0],[0.293,0.033],[-0.279,0]],"o":[[-0.308,0.033],[-0.294,0],[0.265,0.016],[0.338,0]],"v":[[3.944,14.359],[3.004,14.392],[2.122,14.359],[2.945,14.376]]}],"t":13.6},{"o":{"x":0.167,"y":0},"i":{"x":0.667,"y":1},"s":[{"c":true,"i":[[-0.345,0.016],[0.345,0],[0.314,0.031],[-0.298,0]],"o":[[-0.33,0.031],[-0.314,0],[0.283,0.016],[0.361,0]],"v":[[4.692,9.503],[3.687,9.534],[2.745,9.503],[3.624,9.518]]}],"t":19.2},{"o":{"x":0,"y":0},"i":{"x":0.833,"y":1},"s":[{"c":true,"i":[[-0.341,0.016],[0.341,0],[0.31,0.032],[-0.294,0]],"o":[[-0.326,0.032],[-0.31,0],[0.279,0.016],[0.357,0]],"v":[[4.683,4.36],[3.691,4.392],[2.761,4.36],[3.629,4.376]]}],"t":23.2},{"o":{"x":0.036,"y":0},"i":{"x":0.833,"y":0.833},"s":[{"c":true,"i":[[-0.34,0.016],[0.34,0],[0.309,0.032],[-0.294,0]],"o":[[-0.325,0.032],[-0.31,0],[0.279,0.016],[0.356,0]],"v":[[4.233,-0.566],[3.242,-0.535],[2.313,-0.566],[3.18,-0.55]]}],"t":27.2},{"o":{"x":0.167,"y":0.167},"i":{"x":0.944,"y":1},"s":[{"c":true,"i":[[-0.34,0.016],[0.34,0],[0.309,0.031],[-0.294,0]],"o":[[-0.325,0.031],[-0.31,0],[0.279,0.016],[0.356,0]],"v":[[4.192,1.507],[3.202,1.538],[2.274,1.507],[3.14,1.523]]}],"t":31.2},{"o":{"x":0.167,"y":0.167},"i":{"x":0.833,"y":0.833},"s":[{"c":true,"i":[[-0.34,0.015],[0.34,0],[0.309,0.031],[-0.294,0]],"o":[[-0.325,0.031],[-0.31,0],[0.279,0.015],[0.356,0]],"v":[[4.153,7.208],[3.164,7.239],[2.236,7.208],[3.102,7.224]]}],"t":35.2},{"o":{"x":0.167,"y":0.167},"i":{"x":0.436,"y":1},"s":[{"c":true,"i":[[-0.335,0.016],[0.335,0],[0.304,0.032],[-0.29,0]],"o":[[-0.32,0.032],[-0.305,0],[0.275,0.016],[0.351,0]],"v":[[4.506,11.149],[3.531,11.181],[2.616,11.149],[3.47,11.165]]}],"t":37.6},{"o":{"x":0.333,"y":0},"i":{"x":0.833,"y":0.833},"s":[{"c":true,"i":[[-0.331,0.016],[0.331,0],[0.301,0.032],[-0.286,0]],"o":[[-0.316,0.032],[-0.302,0],[0.272,0.016],[0.347,0]],"v":[[4.782,14.238],[3.818,14.27],[2.914,14.238],[3.758,14.254]]}],"t":42.4},{"o":{"x":0.167,"y":0.167},"i":{"x":0.942,"y":1},"s":[{"c":true,"i":[[-0.344,0.016],[0.344,0],[0.313,0.032],[-0.297,0]],"o":[[-0.329,0.032],[-0.313,0],[0.282,0.016],[0.36,0]],"v":[[5.409,7.75],[4.408,7.782],[3.468,7.75],[4.345,7.766]]}],"t":48.8},{"o":{"x":0.167,"y":0.167},"i":{"x":0.833,"y":0.833},"s":[{"c":true,"i":[[-0.351,0.016],[0.351,0],[0.319,0.031],[-0.303,0]],"o":[[-0.335,0.031],[-0.319,0],[0.288,0.016],[0.367,0]],"v":[[5.733,4.395],[4.712,4.426],[3.755,4.395],[4.648,4.411]]}],"t":51.2},{"o":{"x":0.167,"y":0.167},"i":{"x":0.667,"y":1},"s":[{"c":true,"i":[[-0.336,0.016],[0.336,0],[0.305,0.032],[-0.29,0]],"o":[[-0.321,0.032],[-0.306,0],[0.275,0.016],[0.351,0]],"v":[[4.848,0.256],[3.871,0.288],[2.954,0.256],[3.81,0.272]]}],"t":56.8},{"o":{"x":0.187,"y":0},"i":{"x":0.833,"y":0.833},"s":[{"c":true,"i":[[-0.335,0.016],[0.335,0],[0.305,0.032],[-0.29,0]],"o":[[-0.32,0.032],[-0.305,0],[0.275,0.016],[0.351,0]],"v":[[4.205,2.841],[3.229,2.873],[2.314,2.841],[3.168,2.857]]}],"t":60.8},{"o":{"x":0.167,"y":0.167},"i":{"x":0.287,"y":1},"s":[{"c":true,"i":[[-0.352,0.016],[0.352,0],[0.32,0.031],[-0.304,0]],"o":[[-0.336,0.031],[-0.321,0],[0.289,0.016],[0.368,0]],"v":[[4.823,10.567],[3.798,10.598],[2.838,10.567],[3.734,10.583]]}],"t":65.6},{"o":{"x":0.029,"y":0},"i":{"x":0.833,"y":0.833},"s":[{"c":true,"i":[[-0.357,0.015],[0.357,0],[0.324,0.031],[-0.308,0]],"o":[[-0.341,0.031],[-0.325,0],[0.292,0.015],[0.373,0]],"v":[[4.998,13.881],[3.96,13.911],[2.986,13.881],[3.895,13.896]]}],"t":70.4},{"o":{"x":0.167,"y":0.167},"i":{"x":0.72,"y":1},"s":[{"c":true,"i":[[-0.348,0.016],[0.348,0],[0.317,0.032],[-0.301,0]],"o":[[-0.333,0.032],[-0.317,0],[0.286,0.016],[0.365,0]],"v":[[5.73,9.979],[4.716,10.011],[3.764,9.979],[4.652,9.995]]}],"t":76},{"o":{"x":0.333,"y":0},"i":{"x":0.833,"y":0.833},"s":[{"c":true,"i":[[-0.347,0.016],[0.347,0],[0.315,0.032],[-0.3,0]],"o":[[-0.332,0.032],[-0.316,0],[0.285,0.016],[0.363,0]],"v":[[5.415,3.34],[4.405,3.373],[3.457,3.34],[4.342,3.356]]}],"t":80},{"o":{"x":0.167,"y":0.167},"i":{"x":0.833,"y":0.833},"s":[{"c":true,"i":[[-0.359,0.016],[0.359,0],[0.326,0.031],[-0.311,0]],"o":[[-0.343,0.031],[-0.327,0],[0.294,0.016],[0.376,0]],"v":[[4.896,-0.501],[3.851,-0.47],[2.87,-0.501],[3.785,-0.485]]}],"t":84.8},{"o":{"x":0.167,"y":0.167},"i":{"x":0.49,"y":1},"s":[{"c":true,"i":[[-0.339,0.016],[0.339,0],[0.308,0.032],[-0.293,0]],"o":[[-0.324,0.032],[-0.309,0],[0.278,0.016],[0.355,0]],"v":[[4.887,2.107],[3.9,2.139],[2.973,2.107],[3.838,2.123]]}],"t":88.8},{"o":{"x":0.167,"y":0.167},"i":{"x":0.833,"y":0.833},"s":[{"c":true,"i":[[-0.33,0.016],[0.33,0],[0.301,0.032],[-0.286,0]],"o":[[-0.315,0.032],[-0.302,0],[0.272,0.016],[0.347,0]],"v":[[4.324,7.113],[3.365,7.146],[2.465,7.113],[3.305,7.13]]}],"t":93.6},{"o":{"x":0.167,"y":0.167},"i":{"x":0.606,"y":1},"s":[{"c":true,"i":[[-0.326,0.016],[0.326,0],[0.296,0.033],[-0.282,0]],"o":[[-0.311,0.033],[-0.297,0],[0.267,0.016],[0.341,0]],"v":[[4.315,11.095],[3.366,11.128],[2.476,11.095],[3.307,11.112]]}],"t":96.8},{"o":{"x":0.167,"y":0},"i":{"x":0.61,"y":1},"s":[{"c":true,"i":[[-0.323,0.017],[0.323,0],[0.293,0.033],[-0.279,0]],"o":[[-0.308,0.033],[-0.294,0],[0.264,0.017],[0.338,0]],"v":[[4.306,14.856],[3.367,14.889],[2.487,14.856],[3.309,14.873]]}],"t":102.4},{"s":[{"c":true,"i":[[-0.352,0.016],[0.352,0],[0.32,0.031],[-0.304,0]],"o":[[-0.336,0.031],[-0.32,0],[0.288,0.016],[0.368,0]],"v":[[4.969,-0.637],[3.945,-0.605],[2.985,-0.637],[3.881,-0.621]]}],"t":120}],"ix":2}},{"ty":"fl","bm":0,"hd":false,"mn":"ADBE Vector Graphic - Fill","nm":"Fill 1","c":{"a":0,"k":[0.4196,0.5294,0.3922],"ix":4},"r":1,"o":{"a":0,"k":100,"ix":5}},{"ty":"tr","a":{"a":0,"k":[0,0],"ix":1},"s":{"a":0,"k":[100,100],"ix":3},"sk":{"a":0,"k":0,"ix":4},"p":{"a":0,"k":[649.739,34.993],"ix":2},"r":{"a":0,"k":0,"ix":6},"sa":{"a":0,"k":0,"ix":5},"o":{"a":0,"k":100,"ix":7}}]},{"ty":"tr","a":{"a":0,"k":[649.739,34.993],"ix":1},"s":{"a":0,"k":[100,100],"ix":3},"sk":{"a":0,"k":0,"ix":4},"p":{"a":0,"k":[649.739,34.993],"ix":2},"r":{"a":0,"k":0,"ix":6},"sa":{"a":0,"k":0,"ix":5},"o":{"a":0,"k":100,"ix":7}}]},{"ty":"gr","bm":0,"hd":false,"mn":"ADBE Vector Group","nm":"Group 2","ix":2,"cix":2,"np":2,"it":[{"ty":"sh","bm":0,"hd":false,"mn":"ADBE Vector Shape - Group","nm":"Path 1","ix":1,"d":1,"ks":{"a":1,"k":[{"o":{"x":0.167,"y":0},"i":{"x":0.833,"y":0.833},"s":[{"c":true,"i":[[-0.352,0.016],[0.352,0],[0.32,0.031],[-0.304,0]],"o":[[-0.336,0.031],[-0.32,0],[0.288,0.016],[0.368,0]],"v":[[4.97,-0.634],[3.946,-0.602],[2.986,-0.634],[3.882,-0.618]]}],"t":0},{"o":{"x":0.167,"y":0.167},"i":{"x":0.97,"y":1},"s":[{"c":true,"i":[[-0.34,0.025],[0.341,-0.009],[0.31,0.023],[-0.294,0.008]],"o":[[-0.325,0.041],[-0.31,0.008],[0.28,0.008],[0.357,-0.01]],"v":[[5.876,4.035],[4.886,4.094],[3.955,4.088],[4.823,4.08]]}],"t":4.8},{"o":{"x":0.333,"y":0},"i":{"x":0.667,"y":1},"s":[{"c":true,"i":[[-0.329,0.016],[0.329,0],[0.299,0.032],[-0.285,0]],"o":[[-0.315,0.032],[-0.3,0],[0.27,0.016],[0.345,0]],"v":[[4.931,13.305],[3.973,13.337],[3.074,13.305],[3.913,13.321]]}],"t":11.2},{"o":{"x":0.167,"y":0.167},"i":{"x":0.833,"y":0.833},"s":[{"c":true,"i":[[-0.323,0.016],[0.323,0],[0.293,0.033],[-0.279,0]],"o":[[-0.308,0.033],[-0.294,0],[0.265,0.016],[0.338,0]],"v":[[3.944,14.363],[3.005,14.395],[2.123,14.363],[2.946,14.379]]}],"t":13.6},{"o":{"x":0.167,"y":0},"i":{"x":0.667,"y":1},"s":[{"c":true,"i":[[-0.345,0.016],[0.345,0],[0.314,0.031],[-0.298,0]],"o":[[-0.33,0.031],[-0.314,0],[0.283,0.016],[0.361,0]],"v":[[4.693,9.505],[3.688,9.536],[2.745,9.505],[3.625,9.521]]}],"t":19.2},{"o":{"x":0,"y":0},"i":{"x":0.833,"y":1},"s":[{"c":true,"i":[[-0.341,0.016],[0.341,0],[0.31,0.032],[-0.295,0]],"o":[[-0.326,0.032],[-0.31,0],[0.279,0.016],[0.357,0]],"v":[[4.684,4.363],[3.692,4.395],[2.761,4.363],[3.63,4.379]]}],"t":23.2},{"o":{"x":0.036,"y":0},"i":{"x":0.833,"y":0.833},"s":[{"c":true,"i":[[-0.34,0.016],[0.34,0],[0.309,0.032],[-0.294,0]],"o":[[-0.325,0.032],[-0.31,0],[0.279,0.016],[0.356,0]],"v":[[4.234,-0.563],[3.243,-0.532],[2.313,-0.563],[3.181,-0.548]]}],"t":27.2},{"o":{"x":0.167,"y":0.167},"i":{"x":0.944,"y":1},"s":[{"c":true,"i":[[-0.34,0.016],[0.34,0],[0.309,0.031],[-0.294,0]],"o":[[-0.325,0.031],[-0.31,0],[0.279,0.016],[0.356,0]],"v":[[4.193,1.51],[3.203,1.541],[2.274,1.51],[3.141,1.526]]}],"t":31.2},{"o":{"x":0.167,"y":0.167},"i":{"x":0.833,"y":0.833},"s":[{"c":true,"i":[[-0.34,0.015],[0.34,0],[0.309,0.031],[-0.294,0]],"o":[[-0.325,0.031],[-0.31,0],[0.279,0.015],[0.356,0]],"v":[[4.153,7.211],[3.164,7.242],[2.236,7.211],[3.102,7.226]]}],"t":35.2},{"o":{"x":0.167,"y":0.167},"i":{"x":0.436,"y":1},"s":[{"c":true,"i":[[-0.335,0.016],[0.335,0],[0.304,0.032],[-0.29,0]],"o":[[-0.32,0.032],[-0.305,0],[0.275,0.016],[0.351,0]],"v":[[4.506,11.152],[3.531,11.184],[2.616,11.152],[3.47,11.168]]}],"t":37.6},{"o":{"x":0.333,"y":0},"i":{"x":0.833,"y":0.833},"s":[{"c":true,"i":[[-0.331,0.016],[0.331,0],[0.301,0.032],[-0.286,0]],"o":[[-0.316,0.032],[-0.302,0],[0.272,0.016],[0.347,0]],"v":[[4.783,14.241],[3.819,14.274],[2.914,14.241],[3.759,14.257]]}],"t":42.4},{"o":{"x":0.167,"y":0.167},"i":{"x":0.942,"y":1},"s":[{"c":true,"i":[[-0.344,0.016],[0.344,0],[0.313,0.032],[-0.297,0]],"o":[[-0.329,0.032],[-0.313,0],[0.282,0.016],[0.36,0]],"v":[[5.41,7.753],[4.408,7.785],[3.469,7.753],[4.345,7.769]]}],"t":48.8},{"o":{"x":0.167,"y":0.167},"i":{"x":0.833,"y":0.833},"s":[{"c":true,"i":[[-0.351,0.016],[0.351,0],[0.319,0.031],[-0.303,0]],"o":[[-0.335,0.031],[-0.319,0],[0.287,0.016],[0.367,0]],"v":[[5.734,4.398],[4.713,4.429],[3.755,4.398],[4.649,4.413]]}],"t":51.2},{"o":{"x":0.167,"y":0.167},"i":{"x":0.667,"y":1},"s":[{"c":true,"i":[[-0.336,0.016],[0.336,0],[0.305,0.032],[-0.29,0]],"o":[[-0.321,0.032],[-0.306,0],[0.275,0.016],[0.351,0]],"v":[[4.849,0.259],[3.872,0.291],[2.955,0.259],[3.81,0.275]]}],"t":56.8},{"o":{"x":0.187,"y":0},"i":{"x":0.833,"y":0.833},"s":[{"c":true,"i":[[-0.335,0.016],[0.335,0],[0.305,0.032],[-0.29,0]],"o":[[-0.32,0.032],[-0.305,0],[0.275,0.016],[0.351,0]],"v":[[4.205,2.844],[3.23,2.876],[2.314,2.844],[3.169,2.86]]}],"t":60.8},{"o":{"x":0.167,"y":0.167},"i":{"x":0.287,"y":1},"s":[{"c":true,"i":[[-0.352,0.016],[0.352,0],[0.32,0.031],[-0.304,0]],"o":[[-0.336,0.031],[-0.321,0],[0.288,0.016],[0.368,0]],"v":[[4.823,10.57],[3.799,10.601],[2.838,10.57],[3.735,10.586]]}],"t":65.6},{"o":{"x":0.029,"y":0},"i":{"x":0.833,"y":0.833},"s":[{"c":true,"i":[[-0.357,0.015],[0.357,0],[0.324,0.031],[-0.308,0]],"o":[[-0.341,0.031],[-0.325,0],[0.292,0.015],[0.373,0]],"v":[[4.999,13.883],[3.961,13.914],[2.987,13.883],[3.896,13.899]]}],"t":70.4},{"o":{"x":0.167,"y":0.167},"i":{"x":0.72,"y":1},"s":[{"c":true,"i":[[-0.348,0.016],[0.348,0],[0.317,0.032],[-0.301,0]],"o":[[-0.333,0.032],[-0.317,0],[0.286,0.016],[0.365,0]],"v":[[5.731,9.982],[4.717,10.014],[3.765,9.982],[4.653,9.998]]}],"t":76},{"o":{"x":0.333,"y":0},"i":{"x":0.833,"y":0.833},"s":[{"c":true,"i":[[-0.347,0.016],[0.347,0],[0.315,0.032],[-0.3,0]],"o":[[-0.332,0.032],[-0.316,0],[0.285,0.016],[0.363,0]],"v":[[5.416,3.343],[4.405,3.376],[3.458,3.343],[4.342,3.359]]}],"t":80},{"o":{"x":0.167,"y":0.167},"i":{"x":0.833,"y":0.833},"s":[{"c":true,"i":[[-0.359,0.016],[0.359,0],[0.326,0.031],[-0.31,0]],"o":[[-0.343,0.031],[-0.327,0],[0.295,0.016],[0.376,0]],"v":[[4.897,-0.498],[3.851,-0.467],[2.87,-0.498],[3.786,-0.483]]}],"t":84.8},{"o":{"x":0.167,"y":0.167},"i":{"x":0.49,"y":1},"s":[{"c":true,"i":[[-0.339,0.016],[0.339,0],[0.308,0.032],[-0.293,0]],"o":[[-0.324,0.032],[-0.309,0],[0.278,0.016],[0.355,0]],"v":[[4.888,2.11],[3.9,2.142],[2.974,2.11],[3.839,2.126]]}],"t":88.8},{"o":{"x":0.167,"y":0.167},"i":{"x":0.833,"y":0.833},"s":[{"c":true,"i":[[-0.33,0.016],[0.33,0],[0.299,0.032],[-0.285,0]],"o":[[-0.315,0.032],[-0.302,0],[0.272,0.016],[0.347,0]],"v":[[4.325,7.116],[3.365,7.149],[2.465,7.116],[3.305,7.133]]}],"t":93.6},{"o":{"x":0.167,"y":0.167},"i":{"x":0.606,"y":1},"s":[{"c":true,"i":[[-0.326,0.016],[0.326,0],[0.296,0.033],[-0.282,0]],"o":[[-0.311,0.033],[-0.297,0],[0.267,0.016],[0.341,0]],"v":[[4.315,11.099],[3.367,11.131],[2.477,11.099],[3.307,11.115]]}],"t":96.8},{"o":{"x":0.167,"y":0},"i":{"x":0.61,"y":1},"s":[{"c":true,"i":[[-0.323,0.017],[0.323,0],[0.293,0.033],[-0.279,0]],"o":[[-0.308,0.033],[-0.294,0],[0.264,0.017],[0.338,0]],"v":[[4.307,14.859],[3.368,14.892],[2.487,14.859],[3.309,14.876]]}],"t":102.4},{"s":[{"c":true,"i":[[-0.352,0.016],[0.352,0],[0.32,0.031],[-0.304,0]],"o":[[-0.336,0.031],[-0.32,0],[0.288,0.016],[0.368,0]],"v":[[4.97,-0.634],[3.946,-0.602],[2.986,-0.634],[3.882,-0.618]]}],"t":120}],"ix":2}},{"ty":"fl","bm":0,"hd":false,"mn":"ADBE Vector Graphic - Fill","nm":"Fill 1","c":{"a":0,"k":[0.4196,0.5294,0.3922],"ix":4},"r":1,"o":{"a":0,"k":100,"ix":5}},{"ty":"tr","a":{"a":0,"k":[0,0],"ix":1},"s":{"a":0,"k":[100,100],"ix":3},"sk":{"a":0,"k":0,"ix":4},"p":{"a":0,"k":[657.535,70.687],"ix":2},"r":{"a":0,"k":0,"ix":6},"sa":{"a":0,"k":0,"ix":5},"o":{"a":0,"k":100,"ix":7}}]},{"ty":"gr","bm":0,"hd":false,"mn":"ADBE Vector Group","nm":"Group 2","ix":2,"cix":2,"np":2,"it":[{"ty":"sh","bm":0,"hd":false,"mn":"ADBE Vector Shape - Group","nm":"Path 1","ix":1,"d":1,"ks":{"a":1,"k":[{"o":{"x":0.167,"y":0},"i":{"x":0.833,"y":0.833},"s":[{"c":true,"i":[[-1.244,-25.157],[19.461,-0.931],[0.288,0.016],[0.368,0],[0,0],[0.16,0.016],[1.209,24.913],[-9.025,31.725]],"o":[[1.104,22.325],[-0.288,0.016],[-0.352,0.016],[0,0],[-0.16,0],[-21.169,0.312],[-0.85,-17.512],[0,0]],"v":[[41.11,-4.715],[5.859,35.04],[4.995,35.056],[3.907,35.072],[3.49,35.072],[3.01,35.056],[-33.713,-3.89],[4.658,-76.748]]}],"t":0},{"o":{"x":0.167,"y":0.167},"i":{"x":0.97,"y":1},"s":[{"c":true,"i":[[-4.104,-25.788],[18.823,-1.46],[0.28,0.008],[0.357,-0.01],[0,0],[0.156,0.012],[0.729,26.463],[-11.237,28.617]],"o":[[3.876,23.855],[-0.278,0.024],[-0.34,0.025],[0,0],[-0.155,0.004],[-20.494,0.877],[-0.486,-20.128],[0,0]],"v":[[39.935,-2.456],[6.738,39.686],[5.901,39.725],[4.848,39.77],[4.445,39.781],[3.979,39.778],[-32.496,0.913],[7.505,-73.996]]}],"t":4.8},{"o":{"x":0.333,"y":0},"i":{"x":0.667,"y":1},"s":[{"c":true,"i":[[-5.654,-26.66],[18.221,-0.958],[0.27,0.016],[0.345,0],[0,0],[0.15,0.016],[-1.259,28.109],[-15.152,24.706]],"o":[[5.442,25.66],[-0.269,0.016],[-0.329,0.016],[0,0],[-0.15,0],[-19.82,0.32],[1.025,-22.884],[0,0]],"v":[[39.145,6.225],[5.765,48.978],[4.956,48.994],[3.938,49.011],[3.548,49.011],[3.099,48.994],[-30.909,8.199],[14.093,-65.81]]}],"t":11.2},{"o":{"x":0.167,"y":0.167},"i":{"x":0.833,"y":0.833},"s":[{"c":true,"i":[[-6.177,-30.314],[17.865,-0.971],[0.265,0.016],[0.338,0],[0,0],[0.147,0.016],[1.466,18.581],[-30.412,32.25]],"o":[[3.382,16.594],[-0.264,0.016],[-0.323,0.016],[0,0],[-0.147,0],[-19.433,0.325],[-1.623,-20.579],[0,0]],"v":[[40.609,15.659],[4.763,50.036],[3.969,50.052],[2.971,50.069],[2.588,50.069],[2.148,50.052],[-31.564,19.413],[17.277,-62.998]]}],"t":13.6},{"o":{"x":0.167,"y":0},"i":{"x":0.667,"y":1},"s":[{"c":true,"i":[[-13.101,-35.393],[19.101,-0.917],[0.283,0.016],[0.361,0],[0,0],[0.157,0.016],[1.174,17.585],[-30.303,22.885]],"o":[[1.524,16.232],[-0.282,0.016],[-0.345,0.016],[0,0],[-0.157,0],[-20.778,0.307],[-1.61,-24.122],[0,0]],"v":[[44.217,11.02],[5.566,45.18],[4.718,45.195],[3.65,45.211],[3.241,45.211],[2.77,45.195],[-33.274,16.249],[24.013,-62.498]]}],"t":19.2},{"o":{"x":0,"y":0},"i":{"x":0.833,"y":1},"s":[{"c":true,"i":[[-14.093,-37.063],[18.857,-0.945],[0.279,0.016],[0.357,0],[0,0],[0.155,0.016],[-1.295,18.106],[-29.03,20.036]],"o":[[4.482,11.787],[-0.279,0.016],[-0.341,0.016],[0,0],[-0.155,0],[-20.511,0.316],[2.162,-30.228],[0,0]],"v":[[43.083,4.44],[5.546,40.037],[4.709,40.053],[3.655,40.069],[3.251,40.069],[2.786,40.053],[-32.046,8.355],[25.648,-70.623]]}],"t":23.2},{"o":{"x":0.036,"y":0},"i":{"x":0.833,"y":0.833},"s":[{"c":true,"i":[[-9.049,-40.93],[18.837,-0.933],[0.279,0.016],[0.356,0],[0,0],[0.155,0.016],[-0.367,20.481],[-20.106,15.221]],"o":[[2.935,16.773],[-0.278,0.016],[-0.34,0.016],[0,0],[-0.155,0],[-20.49,0.312],[1.038,-25.301],[0,0]],"v":[[41.206,0.569],[5.095,35.111],[4.259,35.127],[3.206,35.142],[2.803,35.142],[2.338,35.127],[-31.149,1.037],[19.097,-78.344]]}],"t":27.2},{"o":{"x":0.167,"y":0.167},"i":{"x":0.944,"y":1},"s":[{"c":true,"i":[[-4.815,-44.177],[18.82,-0.922],[0.279,0.016],[0.356,0],[0,0],[0.155,0.016],[0.413,22.476],[-10.432,24.922]],"o":[[1.635,20.958],[-0.278,0.016],[-0.34,0.016],[0,0],[-0.155,0],[-20.471,0.309],[-0.414,-28.542],[0,0]],"v":[[41.531,0.481],[5.054,37.184],[4.218,37.2],[3.166,37.216],[2.763,37.216],[2.299,37.2],[-33.471,2.92],[6.054,-76.865]]}],"t":31.2},{"o":{"x":0.167,"y":0.167},"i":{"x":0.833,"y":0.833},"s":[{"c":true,"i":[[-0.712,-47.323],[18.803,-0.912],[0.279,0.015],[0.356,0],[0,0],[0.155,0.015],[1.168,24.409],[-1.057,34.323]],"o":[[0.376,25.014],[-0.278,0.015],[-0.34,0.015],[0,0],[-0.155,0],[-20.453,0.305],[-0.821,-17.157],[0,0]],"v":[[43.323,5.81],[5.013,42.885],[4.178,42.901],[3.127,42.916],[2.725,42.916],[2.261,42.901],[-35.721,4.744],[-10.768,-71.248]]}],"t":35.2},{"o":{"x":0.167,"y":0.167},"i":{"x":0.436,"y":1},"s":[{"c":true,"i":[[-0.145,-55.642],[18.536,-0.939],[0.275,0.016],[0.351,0],[0,0],[0.153,0.016],[0.689,25.146],[10.025,35.328]],"o":[[0.094,25.753],[-0.274,0.016],[-0.335,0.016],[0,0],[-0.153,0],[-20.162,0.314],[-0.7,-25.557],[0,0]],"v":[[41.546,7.551],[5.354,46.826],[4.531,46.842],[3.495,46.858],[3.098,46.858],[2.641,46.842],[-34.184,8.56],[-20.035,-71.272]]}],"t":37.6},{"o":{"x":0.333,"y":0},"i":{"x":0.833,"y":0.833},"s":[{"c":true,"i":[[0.299,-62.162],[18.326,-0.96],[0.271,0.016],[0.347,0],[0,0],[0.151,0.016],[1.138,25.693],[14.273,33.636]],"o":[[-0.127,26.332],[-0.271,0.016],[-0.331,0.016],[0,0],[-0.151,0],[-19.934,0.321],[-0.8,-18.059],[0,0]],"v":[[38.816,8.915],[5.622,49.915],[4.808,49.931],[3.783,49.947],[3.391,49.947],[2.939,49.931],[-31.642,9.767],[-25.514,-75.313]]}],"t":42.4},{"o":{"x":0.167,"y":0.167},"i":{"x":0.942,"y":1},"s":[{"c":true,"i":[[1.073,-44.738],[19.036,-0.933],[0.282,0.016],[0.36,0],[0,0],[0.157,0.016],[-0.057,24.967],[3.752,35.794]],"o":[[-0.727,25.563],[-0.281,0.016],[-0.344,0.016],[0,0],[-0.157,0],[-20.707,0.312],[0.241,-24.875],[0,0]],"v":[[40.761,3.605],[6.28,43.427],[5.434,43.443],[4.37,43.459],[3.963,43.459],[3.494,43.443],[-33.005,2.455],[-13.777,-74.827]]}],"t":48.8},{"o":{"x":0.167,"y":0.167},"i":{"x":0.833,"y":0.833},"s":[{"c":true,"i":[[1.473,-35.726],[19.404,-0.919],[0.287,0.016],[0.367,0],[0,0],[0.16,0.016],[-0.675,24.592],[-1.689,36.91]],"o":[[-1.038,25.164],[-0.287,0.016],[-0.351,0.016],[0,0],[-0.16,0],[-21.106,0.307],[0.779,-28.4],[0,0]],"v":[[41.767,0.86],[6.62,40.072],[5.758,40.088],[4.674,40.103],[4.259,40.103],[3.78,40.088],[-33.71,-1.326],[-5.051,-76.123]]}],"t":51.2},{"o":{"x":0.167,"y":0.167},"i":{"x":0.667,"y":1},"s":[{"c":true,"i":[[-2.118,-32.278],[18.58,-0.957],[0.275,0.016],[0.351,0],[0,0],[0.153,0.016],[-0.6,25.628],[-14.263,26.972]],"o":[[1.543,23.516],[-0.274,0.016],[-0.336,0.016],[0,0],[-0.153,0],[-20.211,0.32],[0.623,-26.624],[0,0]],"v":[[39.697,-2.138],[5.699,35.932],[4.874,35.949],[3.835,35.965],[3.438,35.965],[2.98,35.949],[-31.591,-5.447],[12.102,-81.123]]}],"t":56.8},{"o":{"x":0.187,"y":0},"i":{"x":0.833,"y":0.833},"s":[{"c":true,"i":[[-2.687,-34.962],[18.546,-0.961],[0.275,0.016],[0.351,0],[0,0],[0.153,0.016],[-0.576,25.722],[-19.087,23.02]],"o":[[1.995,25.959],[-0.274,0.016],[-0.335,0.016],[0,0],[-0.153,0],[-20.173,0.322],[0.575,-25.674],[0,0]],"v":[[39.12,1.293],[5.054,38.518],[4.23,38.534],[3.193,38.55],[2.797,38.55],[2.339,38.534],[-31.657,-2.391],[16.977,-77.373]]}],"t":60.8},{"o":{"x":0.167,"y":0.167},"i":{"x":0.287,"y":1},"s":[{"c":true,"i":[[-0.869,-27.587],[19.472,-0.92],[0.289,0.016],[0.368,0],[0,0],[0.16,0.016],[-0.605,24.642],[-18.32,26.973]],"o":[[-1.167,20.198],[-0.288,0.016],[-0.352,0.016],[0,0],[-0.16,0],[-21.181,0.308],[0.603,-24.596],[0,0]],"v":[[42.533,12.179],[5.713,46.244],[4.848,46.26],[3.76,46.276],[3.343,46.276],[2.863,46.26],[-34.285,7.482],[15.238,-64.378]]}],"t":65.6},{"o":{"x":0.029,"y":0},"i":{"x":0.833,"y":0.833},"s":[{"c":true,"i":[[-0.353,-25.496],[19.734,-0.909],[0.292,0.015],[0.373,0],[0,0],[0.162,0.015],[-0.613,24.335],[-18.102,28.093]],"o":[[0.341,24.643],[-0.292,0.015],[-0.357,0.015],[0,0],[-0.162,0],[-21.466,0.304],[0.612,-24.29],[0,0]],"v":[[41.093,14.624],[5.9,49.558],[5.023,49.573],[3.92,49.589],[3.498,49.589],[3.012,49.573],[-34.227,11.564],[11.696,-60.374]]}],"t":70.4},{"o":{"x":0.167,"y":0.167},"i":{"x":0.72,"y":1},"s":[{"c":true,"i":[[-3.783,-29.146],[19.279,-0.953],[0.286,0.016],[0.365,0],[0,0],[0.159,0.016],[1.56,25.449],[-1.241,22.34]],"o":[[3.314,25.834],[-0.285,0.016],[-0.348,0.016],[0,0],[-0.159,0],[-20.971,0.319],[-1.094,-19.236],[0,0]],"v":[[37.957,1.826],[6.612,45.656],[5.756,45.672],[4.678,45.688],[4.265,45.688],[3.79,45.672],[-31.591,4.961],[5.129,-73.218]]}],"t":76},{"o":{"x":0.333,"y":0},"i":{"x":0.833,"y":0.833},"s":[{"c":true,"i":[[-4.358,-29.758],[19.203,-0.96],[0.285,0.016],[0.363,0],[0,0],[0.158,0.016],[1.925,25.636],[1.587,21.375]],"o":[[3.813,26.034],[-0.285,0.016],[-0.347,0.016],[0,0],[-0.158,0],[-20.888,0.321],[-1.381,-18.388],[0,0]],"v":[[39.036,-2.802],[6.293,39.017],[5.44,39.033],[4.367,39.049],[3.956,39.049],[3.483,39.033],[-32.754,-1.11],[4.028,-75.373]]}],"t":80},{"o":{"x":0.167,"y":0.167},"i":{"x":0.833,"y":0.833},"s":[{"c":true,"i":[[-7.895,-30.997],[19.877,-0.929],[0.294,0.016],[0.376,0],[0,0],[0.164,0.016],[0.17,24.716],[-3.221,17.343]],"o":[[4.707,22.159],[-0.294,0.016],[-0.359,0.016],[0,0],[-0.164,0],[-21.621,0.311],[0.611,-21.75],[0,0]],"v":[[41.409,-4.301],[5.804,35.176],[4.922,35.192],[3.811,35.207],[3.385,35.207],[2.895,35.192],[-34.221,-3.309],[9.862,-75.023]]}],"t":84.8},{"o":{"x":0.167,"y":0.167},"i":{"x":0.49,"y":1},"s":[{"c":true,"i":[[-12.938,-35.492],[18.777,-0.949],[0.278,0.016],[0.355,0],[0,0],[0.155,0.016],[-2.792,25.1],[-10.923,11.935]],"o":[[5.677,17.39],[-0.278,0.016],[-0.339,0.016],[0,0],[-0.155,0],[-20.425,0.318],[3.881,-29.084],[0,0]],"v":[[42.155,-0.845],[5.747,37.784],[4.913,37.8],[3.863,37.816],[3.462,37.816],[2.999,37.8],[-31.431,-0.949],[19.95,-73.984]]}],"t":88.8},{"o":{"x":0.167,"y":0.167},"i":{"x":0.833,"y":0.833},"s":[{"c":true,"i":[[-15.413,-37.697],[18.237,-0.959],[0.27,0.016],[0.345,0],[0,0],[0.15,0.016],[-4.245,25.288],[-14.702,9.282]],"o":[[6.153,15.05],[-0.269,0.016],[-0.33,0.016],[0,0],[-0.15,0],[-19.838,0.321],[5.486,-32.682],[0,0]],"v":[[41.962,4.577],[5.159,42.79],[4.35,42.806],[3.33,42.823],[2.94,42.823],[2.49,42.806],[-30.621,3.935],[24.34,-69.748]]}],"t":93.6},{"o":{"x":0.167,"y":0.167},"i":{"x":0.606,"y":1},"s":[{"c":true,"i":[[-13.539,-36.918],[18.037,-0.97],[0.267,0.016],[0.341,0],[0,0],[0.148,0.016],[-3.462,25.627],[-15.671,9.969]],"o":[[5.613,16.701],[-0.266,0.016],[-0.326,0.016],[0,0],[-0.148,0],[-19.62,0.325],[4.566,-31.104],[0,0]],"v":[[41.024,7.757],[5.141,46.772],[4.34,46.788],[3.332,46.805],[2.946,46.805],[2.501,46.788],[-30.424,7.306],[23.536,-65.967]]}],"t":96.8},{"o":{"x":0.167,"y":0},"i":{"x":0.61,"y":1},"s":[{"c":true,"i":[[-11.768,-36.182],[17.848,-0.98],[0.264,0.017],[0.338,0],[0,0],[0.147,0.017],[-2.723,25.948],[-12.726,15.555]],"o":[[5.103,18.26],[-0.264,0.017],[-0.323,0.017],[0,0],[-0.147,0],[-19.414,0.328],[3.697,-29.613],[0,0]],"v":[[40.138,10.759],[5.124,50.533],[4.332,50.549],[3.334,50.566],[2.952,50.566],[2.512,50.549],[-30.238,10.49],[19.617,-65.312]]}],"t":102.4},{"s":[{"c":true,"i":[[-1.244,-25.157],[19.461,-0.931],[0.288,0.016],[0.368,0],[0,0],[0.16,0.016],[1.209,24.913],[-9.025,31.725]],"o":[[1.104,22.325],[-0.288,0.016],[-0.352,0.016],[0,0],[-0.16,0],[-21.169,0.312],[-0.85,-17.512],[0,0]],"v":[[41.11,-4.715],[5.859,35.04],[4.995,35.056],[3.907,35.072],[3.49,35.072],[3.01,35.056],[-33.713,-3.89],[4.658,-76.748]]}],"t":120}],"ix":2}},{"ty":"fl","bm":0,"hd":false,"mn":"ADBE Vector Graphic - Fill","nm":"Fill 1","c":{"a":0,"k":[0.6118,0.6549,0.5529],"ix":4},"r":1,"o":{"a":0,"k":100,"ix":5}},{"ty":"tr","a":{"a":0,"k":[0,0],"ix":1},"s":{"a":0,"k":[100,100],"ix":3},"sk":{"a":0,"k":0,"ix":4},"p":{"a":0,"k":[336.992,376.72],"ix":2},"r":{"a":0,"k":0,"ix":6},"sa":{"a":0,"k":0,"ix":5},"o":{"a":0,"k":50,"ix":7}}]},{"ty":"gr","bm":0,"hd":false,"mn":"ADBE Vector Group","nm":"Group 2","ix":2,"cix":2,"np":2,"it":[{"ty":"sh","bm":0,"hd":false,"mn":"ADBE Vector Shape - Group","nm":"Path 1","ix":1,"d":1,"ks":{"a":1,"k":[{"o":{"x":0.333,"y":0},"i":{"x":0.833,"y":1},"s":[{"c":true,"i":[[0,-35.213],[39.581,0.223],[0.295,0.016],[0.36,0],[0.311,0.016],[0,43.633],[-0.589,3.013],[2.165,21.437],[-3.439,-2.195],[-6.593,-4.607],[-4.446,18.579],[-2.434,-3.465]],"o":[[0,43.233],[-0.311,0.016],[-0.36,0.016],[-0.311,0],[-38.907,1.509],[0,-2.996],[1.715,-21.621],[-0.404,-4],[4.776,3.048],[13.315,-17.764],[0.98,-4.094],[17.752,25.277]],"v":[[70.963,-12.903],[4.622,63.916],[3.722,63.932],[2.625,63.948],[1.675,63.932],[-64.463,-13.653],[-63.547,-22.659],[-54.614,-91.146],[-47.061,-95.616],[-29.589,-83.954],[1.008,-138.401],[9.839,-140.098]]}],"t":0},{"o":{"x":0.067,"y":0},"i":{"x":0.849,"y":1},"s":[{"c":true,"i":[[-0.656,-16.944],[38.022,-1.067],[0.3,0.015],[0.366,0],[0.317,0.015],[0,41.514],[-0.599,2.866],[-5.811,17.377],[-2.052,-0.001],[-4.984,0.04],[-9.846,17.46],[-0.882,-3.674]],"o":[[0.749,38.736],[-0.316,0.015],[-0.366,0.015],[-0.316,0],[-38.488,-0.503],[0,-2.851],[1.744,-20.571],[0.734,-2.82],[3.171,-0.63],[13.542,-16.902],[1.893,-3.511],[12.17,41.539]],"v":[[71.714,1.381],[4.262,69.037],[3.347,69.053],[2.231,69.068],[1.266,69.053],[-68.287,-4.051],[-67.354,-12.619],[-47.909,-70.772],[-42.65,-74.697],[-30.53,-71.651],[12.732,-131.647],[20.215,-132.139]]}],"t":8},{"o":{"x":0.333,"y":0},"i":{"x":0.833,"y":0.833},"s":[{"c":true,"i":[[-0.719,-23.003],[34.413,-1.145],[0.271,0.016],[0.331,0],[0.287,0.016],[0,44.553],[-0.542,3.076],[-11.195,15.998],[-0.786,1.832],[-3.235,3.927],[-12.854,18.548],[0.382,-4.274]],"o":[[1.233,39.466],[-0.286,0.016],[-0.331,0.016],[-0.286,0],[-34.835,-0.54],[0,-3.06],[1.579,-22.077],[1.512,-2.16],[1.621,-3.776],[12.256,-18.139],[2.378,-3.431],[-5.793,64.789]],"v":[[64.98,2.775],[4.375,76.035],[3.547,76.051],[2.537,76.068],[1.663,76.051],[-61.287,-2.403],[-60.443,-11.598],[-36.218,-62.576],[-33.252,-66.499],[-27.114,-74.95],[19.099,-141.497],[24.761,-141.039]]}],"t":15.2},{"o":{"x":0.167,"y":0.167},"i":{"x":0.667,"y":1},"s":[{"c":true,"i":[[-0.037,-25.396],[32.269,1.054],[0.276,0.016],[0.337,0],[0.292,0.016],[0,44.267],[-0.552,3.056],[-8.2,23.187],[-2.196,-0.467],[-4.955,-0.945],[-8.727,18.827],[-1.042,-3.899]],"o":[[0.062,42.033],[-0.291,0.016],[-0.337,0.016],[-0.291,0],[-39.969,0.788],[0,-3.04],[1.607,-21.935],[0.435,-3.227],[3.277,0.116],[12.48,-18.022],[1.705,-3.791],[13.371,82.232]],"v":[[67.152,7.78],[3.819,78.008],[2.975,78.024],[1.947,78.04],[1.057,78.024],[-63.843,-1.694],[-62.983,-10.83],[-40.462,-64.125],[-35.104,-68.383],[-28.246,-68.227],[14.824,-133.719],[21.468,-134.92]]}],"t":20},{"o":{"x":0.333,"y":0},"i":{"x":0.667,"y":1},"s":[{"c":true,"i":[[-1.75,-27.158],[37.604,0.225],[0.28,0.016],[0.342,0],[0.296,0.016],[0,44.05],[-0.56,3.041],[2.057,21.641],[-3.268,-2.216],[-6.264,-4.651],[-5.588,19.039],[-2.125,-3.615]],"o":[[2.807,43.555],[-0.295,0.016],[-0.342,0.016],[-0.295,0],[-36.964,1.524],[0,-3.025],[1.629,-21.828],[-0.384,-4.038],[4.537,3.077],[12.65,-17.934],[1.193,-4.065],[16.022,27.252]],"v":[[69.463,7.845],[2.736,76.647],[1.88,76.664],[0.838,76.68],[-0.064,76.664],[-65.787,-1.155],[-64.916,-10.247],[-50.292,-70.145],[-43.115,-74.658],[-29.766,-66.634],[8.052,-125.602],[15.442,-128.065]]}],"t":24},{"o":{"x":0.333,"y":0},"i":{"x":0.833,"y":0.833},"s":[{"c":true,"i":[[0,-36.95],[35.047,-1.177],[0.276,0.017],[0.338,0],[0.292,0.017],[0,45.786],[-0.552,3.161],[2.03,22.494],[-3.224,-2.303],[-6.181,-4.835],[-4.168,19.496],[-2.281,-3.636]],"o":[[0,45.366],[-0.291,0.017],[-0.338,0.017],[-0.291,0],[-35.477,-0.555],[0,-3.144],[1.608,-22.688],[-0.379,-4.197],[4.477,3.198],[12.482,-18.641],[0.919,-4.296],[16.641,26.525]],"v":[[67.463,-12.706],[4.335,67.903],[3.491,67.92],[2.463,67.937],[1.573,67.92],[-62.537,-12.706],[-61.677,-22.156],[-51.194,-94.809],[-43.363,-95.5],[-26.985,-83.262],[2.197,-142.146],[7.976,-144.927]]}],"t":30.4},{"o":{"x":0.167,"y":0.167},"i":{"x":0.667,"y":1},"s":[{"c":true,"i":[[0,-36.339],[36.643,-0.684],[0.283,0.017],[0.345,0],[0.299,0.017],[0,45.028],[-0.546,3.109],[2.007,22.122],[-3.188,-2.265],[-6.111,-4.755],[-4.266,19.173],[-2.335,-3.576]],"o":[[0,44.615],[-0.298,0.017],[-0.345,0.017],[-0.298,0],[-36.684,0.172],[0,-3.092],[1.59,-22.313],[-0.374,-4.128],[4.426,3.145],[12.341,-18.332],[0.94,-4.225],[17.032,26.086]],"v":[[67.375,-12.247],[4.436,66.5],[3.572,66.516],[2.52,66.533],[1.609,66.516],[-61.625,-12.761],[-60.775,-22.055],[-51.147,-97.52],[-43.66,-99.541],[-27.217,-87.506],[2.658,-142.412],[9.247,-144.459]]}],"t":32},{"o":{"x":0.333,"y":0},"i":{"x":0.833,"y":0.833},"s":[{"c":true,"i":[[0,-35.213],[39.581,0.223],[0.295,0.016],[0.36,0],[0.311,0.016],[0,43.633],[-0.534,3.013],[1.964,21.437],[-3.12,-2.195],[-5.982,-4.607],[-4.446,18.579],[-2.434,-3.465]],"o":[[0,43.233],[-0.311,0.016],[-0.36,0.016],[-0.311,0],[-38.907,1.509],[0,-2.996],[1.556,-21.621],[-0.367,-4],[4.333,3.048],[12.081,-17.764],[0.98,-4.094],[17.752,25.277]],"v":[[67.213,-11.403],[4.622,63.916],[3.722,63.932],[2.625,63.948],[1.675,63.932],[-62.787,-12.153],[-61.955,-21.159],[-51.059,-91.146],[-44.206,-95.616],[-28.354,-83.954],[3.508,-142.901],[11.589,-143.598]]}],"t":34.4},{"o":{"x":0.167,"y":0.167},"i":{"x":0.833,"y":0.833},"s":[{"c":true,"i":[[-2.798,-15.618],[37.884,-1.082],[0.298,0.015],[0.365,0],[0.315,0.015],[0,42.088],[-0.597,2.906],[-7.73,16.874],[-1.694,0.513],[-4.548,1.13],[-11.099,17.648],[-0.493,-3.817]],"o":[[3.266,38.922],[-0.315,0.015],[-0.365,0.015],[-0.315,0],[-38.348,-0.51],[0,-2.89],[1.738,-20.855],[1.008,-2.616],[2.751,-1.509],[13.493,-17.135],[2.103,-3.465],[12.571,43.018]],"v":[[70.948,-1.805],[3.749,68.949],[2.836,68.965],[1.725,68.98],[0.763,68.965],[-68.537,-5.148],[-67.608,-13.835],[-44.618,-69.203],[-39.965,-73.101],[-30.918,-72.182],[16.295,-134.273],[20.763,-133.495]]}],"t":40},{"o":{"x":0.167,"y":0.167},"i":{"x":0.667,"y":1},"s":[{"c":true,"i":[[-1.031,-21.822],[35.604,-1.13],[0.281,0.016],[0.343,0],[0.296,0.016],[0,43.961],[-0.561,3.035],[-10.924,16.038],[-0.932,1.633],[-3.488,3.506],[-12.862,18.32],[0.265,-4.185]],"o":[[1.549,39.177],[-0.296,0.016],[-0.343,0.016],[-0.296,0],[-36.04,-0.533],[0,-3.019],[1.633,-21.784],[1.47,-2.214],[1.815,-3.432],[12.681,-17.898],[2.386,-3.417],[-3.28,61.324]],"v":[[68.309,4.684],[4.538,76.193],[3.681,76.21],[2.637,76.226],[1.732,76.21],[-65.896,-0.703],[-65.023,-9.777],[-37.987,-61.611],[-34.72,-65.51],[-28.041,-72.573],[21.246,-137.814],[25.665,-137.563]]}],"t":44},{"o":{"x":0.333,"y":0},"i":{"x":0.833,"y":0.833},"s":[{"c":true,"i":[[-0.736,-22.86],[35.222,-1.138],[0.278,0.016],[0.339,0],[0.293,0.016],[0,44.275],[-0.555,3.057],[-11.458,15.898],[-0.805,1.82],[-3.311,3.903],[-13.157,18.432],[0.391,-4.247]],"o":[[1.262,39.22],[-0.293,0.016],[-0.339,0.016],[-0.293,0],[-35.654,-0.537],[0,-3.041],[1.616,-21.939],[1.547,-2.147],[1.659,-3.753],[12.545,-18.025],[2.434,-3.409],[-5.93,64.385]],"v":[[66.701,4.602],[4.67,77.405],[3.822,77.421],[2.789,77.437],[1.894,77.421],[-62.537,-0.544],[-61.673,-9.682],[-36.878,-60.342],[-33.843,-64.241],[-27.56,-72.639],[19.74,-138.771],[25.536,-138.316]]}],"t":45.6},{"o":{"x":0.167,"y":0.167},"i":{"x":0.833,"y":0.833},"s":[{"c":true,"i":[[-2.526,-21.745],[34.283,-1.136],[0.27,0.016],[0.33,0],[0.285,0.016],[0,44.18],[-0.54,3.05],[-10.638,17.893],[-1.421,0.73],[-3.982,1.593],[-10.459,18.506],[-0.322,-4.042]],"o":[[0.898,40.383],[-0.285,0.016],[-0.33,0.016],[-0.285,0],[-34.703,-0.535],[0,-3.034],[1.573,-21.892],[1.002,-2.655],[2.358,-1.909],[12.21,-17.987],[1.973,-3.602],[7.501,77.833]],"v":[[65.372,5.304],[4.894,77.905],[4.068,77.921],[3.063,77.937],[2.192,77.921],[-61.27,0.122],[-60.43,-8.996],[-36.149,-64.956],[-32.394,-68.867],[-26.477,-71.819],[17.052,-138.541],[22.962,-137.271]]}],"t":48.8},{"o":{"x":0.167,"y":0.167},"i":{"x":0.833,"y":0.833},"s":[{"c":true,"i":[[-0.198,-31.173],[36.618,-1.095],[0.288,0.016],[0.353,0],[0.305,0.016],[0,42.607],[-0.577,2.942],[-1.517,19.472],[-2.712,-1.134],[-5.676,-2.359],[-6.772,18.037],[-1.66,-3.566]],"o":[[0.34,41.056],[-0.305,0.016],[-0.353,0.016],[-0.305,0],[-37.067,-0.516],[0,-2.926],[1.68,-21.113],[0.124,-3.429],[3.912,1.268],[13.042,-17.346],[1.367,-3.812],[18.435,34.533]],"v":[[68.873,1.2],[4.083,71.137],[3.201,71.152],[2.127,71.168],[1.197,71.152],[-65.787,-3.876],[-64.889,-12.669],[-50.682,-77.784],[-45.17,-81.591],[-29.425,-73.255],[7.611,-132.782],[13.295,-132.247]]}],"t":56},{"o":{"x":0.167,"y":0.167},"i":{"x":0.667,"y":1},"s":[{"c":true,"i":[[0.118,-35.581],[34.681,-1.153],[0.273,0.016],[0.334,0],[0.289,0.016],[0,44.832],[-0.546,3.095],[1.331,21.753],[-3.068,-2.067],[-5.971,-4.335],[-4.575,19.07],[-2.123,-3.594]],"o":[[-0.14,46.689],[-0.288,0.016],[-0.334,0.016],[-0.288,0],[-35.106,-0.543],[0,-3.079],[1.591,-22.215],[-0.278,-4.021],[4.287,2.814],[12.352,-18.252],[0.985,-4.172],[27.685,42.769]],"v":[[68.162,-10.469],[4.05,65.561],[3.215,65.577],[2.197,65.593],[1.316,65.577],[-63.125,-13.118],[-62.274,-22.371],[-51.545,-92.295],[-46.359,-96.563],[-27.325,-83.414],[2.891,-143.09],[7.903,-144.082]]}],"t":60.8},{"o":{"x":0.333,"y":0},"i":{"x":0.833,"y":0.833},"s":[{"c":true,"i":[[0.191,-36.59],[34.238,-1.166],[0.27,0.017],[0.33,0],[0.285,0.017],[0,45.341],[-0.539,3.13],[1.983,22.275],[-3.15,-2.281],[-6.038,-4.788],[-4.072,19.306],[-2.229,-3.601]],"o":[[-0.25,47.978],[-0.285,0.017],[-0.33,0.017],[-0.285,0],[-34.658,-0.549],[0,-3.114],[1.571,-22.467],[-0.37,-4.156],[4.373,3.167],[12.194,-18.459],[0.897,-4.255],[16.257,26.266]],"v":[[66.463,-15.29],[4.042,64.284],[3.218,64.301],[2.213,64.318],[1.344,64.301],[-61.287,-15.54],[-60.447,-24.898],[-50.206,-96.845],[-44.788,-99.99],[26.538,-87.121],[2.732,-145.449],[8.82,-147.712]]}],"t":63.2},{"o":{"x":0.167,"y":0.167},"i":{"x":0.833,"y":0.833},"s":[{"c":true,"i":[[-2.198,-24.644],[35.594,-1.127],[0.28,0.016],[0.343,0],[0.296,0.016],[0,43.847],[-0.561,3.027],[-4.145,20.643],[-2.657,-1.319],[-5.542,-2.751],[-6.507,18.578],[-1.636,-3.642]],"o":[[0.161,44.371],[-0.296,0.016],[-0.343,0.016],[-0.296,0],[-36.03,-0.531],[0,-3.011],[1.633,-21.727],[0.104,-3.601],[3.826,1.564],[12.677,-17.851],[1.316,-3.951],[18.628,44.567]],"v":[[69.162,-5.294],[4.089,68.412],[3.231,68.428],[2.187,68.444],[1.283,68.428],[-65.554,-7.578],[-64.681,-16.628],[-47.073,-81.494],[-43.372,-83.141],[-28.265,-77.759],[9.808,-138.196],[16.211,-139.38]]}],"t":68},{"o":{"x":0.167,"y":0.167},"i":{"x":0.833,"y":0.833},"s":[{"c":true,"i":[[-1.118,-20.744],[37.974,-1.06],[0.299,0.015],[0.366,0],[0.316,0.015],[0,41.225],[-0.598,2.846],[-14.902,17.777],[-1.792,0.368],[-4.67,0.823],[-10.781,17.3],[-0.597,-3.715]],"o":[[0.882,38.041],[-0.316,0.015],[-0.366,0.015],[-0.316,0],[-38.439,-0.5],[0,-2.831],[1.742,-20.428],[0.937,-2.626],[2.866,-1.251],[13.525,-16.784],[2.05,-3.419],[12.101,72.035]],"v":[[71.832,7.432],[4.17,75.657],[3.256,75.672],[2.142,75.687],[1.177,75.672],[-68.912,2.954],[-67.98,-5.555],[-40.885,-59.715],[-36.063,-63.554],[-30.953,-64.675],[17.406,-125.808],[24.362,-125.098]]}],"t":72.8},{"o":{"x":0.167,"y":0.167},"i":{"x":0.833,"y":0.833},"s":[{"c":true,"i":[[-0.785,-22.867],[36.281,-1.141],[0.286,0.016],[0.349,0],[0.302,0.016],[0,44.381],[-0.572,3.064],[-12.019,16.198],[-0.907,1.708],[-3.504,3.666],[-13.231,18.512],[0.316,-4.236]],"o":[[1.26,39.448],[-0.302,0.016],[-0.349,0.016],[-0.302,0],[-36.725,-0.538],[0,-3.048],[1.664,-21.992],[1.532,-2.207],[1.8,-3.565],[12.922,-18.069],[2.458,-3.439],[-4.538,65.601]],"v":[[67.954,6.888],[3.993,79.904],[3.119,79.921],[2.055,79.937],[1.133,79.921],[-65.287,1.757],[-64.397,-7.403],[-38.826,-55.923],[-35.318,-59.537],[-27.488,-68.93],[20.885,-134.183],[25.54,-134.327]]}],"t":76.8},{"o":{"x":0.167,"y":0.167},"i":{"x":0.833,"y":0.833},"s":[{"c":true,"i":[[-3.265,-21.293],[34.694,-1.162],[0.273,0.017],[0.334,0],[0.289,0.017],[0,45.22],[-0.547,3.122],[-7.902,17.759],[-1.403,0.807],[-3.988,1.756],[-10.711,18.935],[-0.288,-4.148]],"o":[[0.927,41.265],[-0.288,0.017],[-0.334,0.017],[-0.289,0],[-35.119,-0.548],[0,-3.105],[1.592,-22.407],[1.041,-2.69],[2.346,-2.053],[12.357,-18.41],[2.018,-3.676],[7.748,61.343]],"v":[[65.537,0.92],[4.412,75.904],[3.576,75.921],[2.559,75.937],[1.678,75.921],[-61.787,-3.708],[-60.936,-13.041],[-38.896,-69.775],[-34.883,-73.923],[-26.46,-74.966],[17.411,-143.762],[21.34,-142.406]]}],"t":80.8},{"o":{"x":0.167,"y":0.167},"i":{"x":0.667,"y":1},"s":[{"c":true,"i":[[-1.185,-30.012],[36.164,-1.132],[0.285,0.016],[0.348,0],[0.301,0.016],[0,44.024],[-0.57,3.04],[-1.503,20.011],[-2.678,-1.096],[-5.605,-2.278],[-6.691,18.629],[-1.639,-3.698]],"o":[[0.336,42.335],[-0.301,0.016],[-0.348,0.016],[-0.301,0],[-36.607,-0.534],[0,-3.023],[1.659,-21.815],[0.123,-3.507],[3.863,1.184],[12.88,-17.923],[1.35,-3.925],[14.005,38.26]],"v":[[67.085,-3.755],[4.191,69.299],[3.32,69.315],[2.259,69.331],[1.341,69.315],[-64.813,-8.208],[-63.926,-17.294],[-46.159,-79.802],[-41.851,-83.42],[-28.265,-77.759],[10.53,-139.526],[15.374,-139.789]]}],"t":84.8},{"o":{"x":0.333,"y":0},"i":{"x":0.833,"y":0.833},"s":[{"c":true,"i":[[0,-34.979],[37.001,-1.114],[0.292,0.016],[0.356,0],[0.308,0.016],[0,43.343],[-0.583,2.993],[2.143,21.294],[-3.404,-2.18],[-6.526,-4.577],[-4.401,18.455],[-2.409,-3.442]],"o":[[0,42.945],[-0.308,0.016],[-0.356,0.016],[-0.308,0],[-37.455,-0.525],[0,-2.977],[1.697,-21.477],[-0.4,-3.973],[4.726,3.028],[13.178,-17.646],[0.97,-4.067],[17.57,25.109]],"v":[[70.713,-8.772],[4.065,65.536],[3.174,65.552],[2.088,65.568],[1.149,65.552],[-66.537,-10.772],[-65.629,-19.718],[-53.437,-87.869],[-48.961,-91.185],[-29.294,-79.35],[3.863,-135.935],[9.228,-137.121]]}],"t":88.8},{"o":{"x":0.167,"y":0.167},"i":{"x":0.833,"y":0.833},"s":[{"c":true,"i":[[0.014,-26.859],[36.979,-1.102],[0.291,0.016],[0.356,0],[0.308,0.016],[0,42.868],[-0.583,2.96],[6.146,20.576],[-2.251,-0.393],[-5.151,-0.788],[-4.338,20.036],[-1.139,-3.723]],"o":[[0.596,40.449],[-0.307,0.016],[-0.356,0.016],[-0.307,0],[-37.432,-0.52],[0,-2.944],[1.696,-21.242],[0.511,-3.097],[3.382,0.011],[13.17,-17.453],[1.683,-3.698],[36.018,52.027]],"v":[[71.367,-10.299],[6.272,64.286],[5.381,64.302],[4.297,64.318],[3.358,64.302],[-66.537,-10.685],[-65.63,-19.533],[-54.807,-92.139],[-50.389,-93.878],[-28.816,-80.239],[3.052,-139.099],[7.695,-138.465]]}],"t":92},{"o":{"x":0.167,"y":0.167},"i":{"x":0.833,"y":0.833},"s":[{"c":true,"i":[[-0.235,-24.792],[35.925,-1.08],[0.283,0.015],[0.346,0],[0.299,0.015],[0,42.005],[-0.566,2.9],[1.406,20.156],[-1.743,0.311],[-4.523,0.135],[-6.255,20.23],[-0.664,-3.777]],"o":[[0.81,38.835],[-0.299,0.015],[-0.346,0.015],[-0.299,0],[-36.365,-0.509],[0,-2.885],[1.648,-20.814],[0.848,-2.706],[2.865,-0.196],[12.795,-17.101],[1.91,-3.495],[28.492,45.527]],"v":[[70.612,-1.832],[4.798,70.226],[3.932,70.242],[2.879,70.257],[1.966,70.242],[-66.096,-4.861],[-65.215,-13.53],[-51.693,-82.469],[-47.744,-84.929],[-28.87,-75.046],[6.718,-134.043],[11.096,-135.339]]}],"t":96},{"o":{"x":0.167,"y":0.167},"i":{"x":0.667,"y":1},"s":[{"c":true,"i":[[-0.633,-21.485],[34.238,-1.044],[0.27,0.015],[0.33,0],[0.285,0.015],[0,40.625],[-0.539,2.805],[-10.32,14.924],[-0.93,1.438],[-3.519,1.613],[-12.246,16.937],[0.096,-3.864]],"o":[[1.15,36.254],[-0.285,0.015],[-0.33,0.015],[-0.285,0],[-34.658,-0.492],[0,-2.79],[1.571,-20.13],[1.387,-2.08],[2.038,-0.527],[12.194,-16.539],[2.274,-3.171],[12.001,69.026]],"v":[[69.405,11.716],[2.439,79.73],[1.614,79.745],[0.61,79.76],[-0.26,79.745],[-65.391,4.458],[-64.551,-3.926],[-40.21,-61.797],[-37.012,-65.411],[-28.955,-66.738],[18.109,-129.854],[22.713,-130.339]]}],"t":102.4},{"o":{"x":0.333,"y":0},"i":{"x":0.833,"y":0.833},"s":[{"c":true,"i":[[-0.764,-22.391],[36.572,-1.115],[0.288,0.016],[0.352,0],[0.305,0.016],[0,43.367],[-0.576,2.994],[-11.897,15.572],[-0.835,1.783],[-3.438,3.823],[-13.661,18.054],[0.26,-4.171]],"o":[[1.311,38.416],[-0.304,0.016],[-0.352,0.016],[-0.304,0],[-37.02,-0.526],[0,-2.978],[1.678,-21.489],[1.607,-2.103],[1.723,-3.676],[13.025,-17.656],[2.527,-3.339],[-4.012,64.48]],"v":[[68.903,2.845],[4.495,74.155],[3.615,74.171],[2.542,74.187],[1.613,74.171],[-65.287,-2.195],[-64.39,-11.145],[-38.27,-59.766],[-35.118,-63.585],[-28.595,-71.811],[21.517,-136.962],[26.16,-137.141]]}],"t":107.2},{"o":{"x":0.167,"y":0.167},"i":{"x":0.667,"y":1},"s":[{"c":true,"i":[[-0.382,-28.802],[38.077,-0.446],[0.291,0.016],[0.356,0],[0.308,0.016],[0,43.5],[-0.583,3.003],[-4.866,18.505],[-2.137,-0.206],[-5.016,-0.392],[-9.054,18.317],[-1.087,-3.818]],"o":[[0.655,40.824],[-0.307,0.016],[-0.356,0.016],[-0.308,0],[-37.964,0.492],[0,-2.987],[1.696,-21.555],[0.601,-3.051],[3.249,-0.314],[13.93,-15.805],[1.753,-3.717],[18.964,53.307]],"v":[[68.433,-2.029],[4.559,69.035],[3.668,69.051],[2.583,69.067],[1.644,69.051],[-64.875,-7.924],[-63.968,-16.902],[-45.317,-79.581],[-41.089,-83.851],[-28.967,-79.757],[11.262,-140.807],[17.249,-142.12]]}],"t":113.6},{"s":[{"c":true,"i":[[0,-35.213],[39.581,0.223],[0.295,0.016],[0.36,0],[0.311,0.016],[0,43.633],[-0.589,3.012],[2.165,21.437],[-3.439,-2.195],[-6.593,-4.607],[-4.446,18.579],[-2.434,-3.465]],"o":[[0,43.233],[-0.311,0.016],[-0.36,0.016],[-0.311,0],[-38.907,1.509],[0,-2.996],[1.715,-21.621],[-0.404,-4],[4.776,3.048],[13.315,-17.764],[0.98,-4.094],[17.752,25.277]],"v":[[70.963,-12.903],[4.622,63.916],[3.722,63.932],[2.625,63.948],[1.675,63.932],[-64.463,-13.653],[-63.547,-22.659],[-54.614,-91.146],[-47.061,-95.616],[-29.589,-83.954],[1.008,-138.401],[9.839,-140.098]]}],"t":120}],"ix":2}},{"ty":"fl","bm":0,"hd":false,"mn":"ADBE Vector Graphic - Fill","nm":"Fill 1","c":{"a":0,"k":[0.6118,0.6549,0.5529],"ix":4},"r":1,"o":{"a":0,"k":100,"ix":5}},{"ty":"tr","a":{"a":0,"k":[0,0],"ix":1},"s":{"a":0,"k":[100,100],"ix":3},"sk":{"a":0,"k":0,"ix":4},"p":{"a":0,"k":[355.662,362.438],"ix":2},"r":{"a":0,"k":0,"ix":6},"sa":{"a":0,"k":0,"ix":5},"o":{"a":0,"k":100,"ix":7}}]}],"v":"5.7.0","fr":48,"op":96,"ip":0,"assets":[]}